pysecspy/__init__.py
pysecspy/const.py
pysecspy/errors.py
pysecspy/secspy_data.py
pysecspy/secspy_server.py
pysecspy-1.3.5.dist-info/LICENSE
pysecspy-1.3.5.dist-info/METADATA
pysecspy-1.3.5.dist-info/WHEEL
pysecspy-1.3.5.dist-info/top_level.txt
pysecspy-1.3.5.dist-info/RECORD
